{
  "root" : {
    "__class" : "RootNode",
    "children" : [
      {
        "__class" : "FrameNode",
        "aspectRatio" : null,
        "blendingEnabled" : 0,
        "blendingMode" : "normal",
        "bottom" : null,
        "centerAnchorX" : 0,
        "centerAnchorY" : 0,
        "children" : [
          {
            "__class" : "FrameNode",
            "aspectRatio" : null,
            "blendingEnabled" : 0,
            "blendingMode" : "normal",
            "bottom" : null,
            "centerAnchorX" : 0.5,
            "centerAnchorY" : 0.19333333333333333,
            "children" : [
              {
                "__class" : "CodeComponentNode",
                "aspectRatio" : null,
                "bottom" : 0,
                "centerAnchorX" : 0.5,
                "centerAnchorY" : 0.5,
                "children" : [

                ],
                "clip" : true,
                "codeComponentIdentifier" : ".\/LocationLookup.tsx_LocationLookup",
                "codeComponentProps" : {
                  "backgroundColor" : "#FFF",
                  "borderRadius" : 4,
                  "fontSize" : 16,
                  "padding" : 16,
                  "paddingBottom" : 16,
                  "paddingLeft" : 56,
                  "paddingPerSide" : true,
                  "paddingRight" : 16,
                  "paddingTop" : 16,
                  "placeholder" : "Zoek op gemeente, woonplaats, adres of postcode",
                  "resultColor" : "hsl(0, 0%, 20%)",
                  "resultLength" : 5,
                  "resultSpacing" : 16,
                  "searchColor" : "#333",
                  "selectBackground" : "rgba(0,0,0,0.05)",
                  "selectColor" : "hsl(203, 83%, 53%)",
                  "value" : "Singel 3"
                },
                "codeOverrideEnabled" : true,
                "codeOverrideFile" : ".\/App.tsx",
                "codeOverrideIdentifier" : ".\/App.tsx_Select",
                "codeOverrideName" : "Select",
                "constraintsLocked" : false,
                "deviceType" : null,
                "exportOptions" : [

                ],
                "fillColor" : "rgba(255,255,255,1)",
                "fillEnabled" : false,
                "fillImage" : null,
                "fillImagePixelHeight" : null,
                "fillImagePixelWidth" : null,
                "fillImageResize" : "fill",
                "fillLinearGradient" : {
                  "__class" : "LinearGradient",
                  "alpha" : 1,
                  "angle" : 180,
                  "stops" : [
                    {
                      "__class" : "GradientColorStop",
                      "position" : 0,
                      "value" : "rgba(0,0,0,0)"
                    },
                    {
                      "__class" : "GradientColorStop",
                      "position" : 1,
                      "value" : "black"
                    }
                  ]
                },
                "fillRadialGradient" : {
                  "__class" : "RadialGradient",
                  "alpha" : 1,
                  "centerAnchorX" : 0.5,
                  "centerAnchorY" : 0.5,
                  "heightFactor" : 0.5,
                  "stops" : [
                    {
                      "__class" : "GradientColorStop",
                      "position" : 0,
                      "value" : "rgba(0,0,0,0)"
                    },
                    {
                      "__class" : "GradientColorStop",
                      "position" : 1,
                      "value" : "black"
                    }
                  ],
                  "widthFactor" : 0.5
                },
                "fillType" : "color",
                "height" : 56,
                "heightType" : 0,
                "id" : "wDldCs1HH",
                "intrinsicHeight" : 56,
                "intrinsicWidth" : 320,
                "left" : 0,
                "locked" : false,
                "name" : null,
                "opacity" : 1,
                "originalid" : null,
                "parentid" : "HSrCgvjbS",
                "previewSettings" : null,
                "radius" : 0,
                "radiusBottomLeft" : 0,
                "radiusBottomRight" : 0,
                "radiusIsRelative" : false,
                "radiusPerCorner" : false,
                "radiusTopLeft" : 0,
                "radiusTopRight" : 0,
                "right" : 0,
                "rotation" : 0,
                "top" : 0,
                "visible" : true,
                "width" : 480,
                "widthType" : 0
              },
              {
                "__class" : "FrameNode",
                "aspectRatio" : 1,
                "blendingEnabled" : 0,
                "blendingMode" : "normal",
                "blur" : 12,
                "blurEnabled" : 0,
                "blurType" : "layer",
                "borderBottom" : 1,
                "borderColor" : "#222",
                "borderEnabled" : 0,
                "borderLeft" : 1,
                "borderPerSide" : false,
                "borderRight" : 1,
                "borderStyle" : "solid",
                "borderTop" : 1,
                "borderWidth" : 1,
                "bottom" : null,
                "boxShadows" : [

                ],
                "brightness" : 100,
                "brightnessEnabled" : 0,
                "centerAnchorX" : 0.058333333333333334,
                "centerAnchorY" : 0.5,
                "children" : [

                ],
                "clip" : true,
                "codeOverrideEnabled" : false,
                "constraintsLocked" : false,
                "contrast" : 100,
                "contrastEnabled" : 0,
                "deviceType" : null,
                "exportOptions" : [
                  {
                    "__class" : "ExportOptions",
                    "enabled" : true,
                    "nameExtension" : "",
                    "nameExtensionMode" : "Suffix",
                    "scale" : 1,
                    "type" : "png"
                  }
                ],
                "fillColor" : "rgba(255,255,255,1)",
                "fillEnabled" : false,
                "fillImage" : null,
                "fillImagePixelHeight" : null,
                "fillImagePixelWidth" : null,
                "fillImageResize" : "fill",
                "fillLinearGradient" : {
                  "__class" : "LinearGradient",
                  "alpha" : 1,
                  "angle" : 180,
                  "stops" : [
                    {
                      "__class" : "GradientColorStop",
                      "position" : 0,
                      "value" : "rgba(0,0,0,0)"
                    },
                    {
                      "__class" : "GradientColorStop",
                      "position" : 1,
                      "value" : "black"
                    }
                  ]
                },
                "fillRadialGradient" : {
                  "__class" : "RadialGradient",
                  "alpha" : 1,
                  "centerAnchorX" : 0.5,
                  "centerAnchorY" : 0.5,
                  "heightFactor" : 0.5,
                  "stops" : [
                    {
                      "__class" : "GradientColorStop",
                      "position" : 0,
                      "value" : "rgba(0,0,0,0)"
                    },
                    {
                      "__class" : "GradientColorStop",
                      "position" : 1,
                      "value" : "black"
                    }
                  ],
                  "widthFactor" : 0.5
                },
                "fillType" : "color",
                "grayscale" : 0,
                "grayScaleEnabled" : 0,
                "height" : 24,
                "heightType" : 0,
                "hueRotate" : 0,
                "hueRotateEnabled" : 0,
                "id" : "S3mbfHlU_",
                "intrinsicHeight" : null,
                "intrinsicWidth" : null,
                "invert" : 0,
                "invertEnabled" : 0,
                "isExternalMaster" : null,
                "isMaster" : false,
                "isTarget" : false,
                "left" : 16,
                "locked" : false,
                "name" : "search",
                "navigationTarget" : null,
                "navigationTransition" : "push",
                "navigationTransitionBackdropColor" : "rgba(4,4,15,.4)",
                "navigationTransitionDirection" : "left",
                "opacity" : 1,
                "originalid" : "@framer\/colebemis.feather-icons-kJVk7KBWG",
                "parentid" : "HSrCgvjbS",
                "previewSettings" : null,
                "radius" : 0,
                "radiusBottomLeft" : 0,
                "radiusBottomRight" : 0,
                "radiusIsRelative" : false,
                "radiusPerCorner" : false,
                "radiusTopLeft" : 0,
                "radiusTopRight" : 0,
                "replicaInfo" : {
                  "master" : "@framer\/colebemis.feather-icons-kJVk7KBWG",
                  "overrides" : {
                    "@framer\/colebemis.feather-icons-kJVk7KBWG" : {
                      "bottom" : null,
                      "centerAnchorX" : 0.058333333333333334,
                      "centerAnchorY" : 0.5,
                      "left" : 16,
                      "right" : null,
                      "top" : null
                    },
                    "@framer\/colebemis.feather-icons-kJVk7KBWG-uDQ947E3A" : {
                      "fillColor" : "#666"
                    }
                  }
                },
                "right" : null,
                "rotation" : 0,
                "saturate" : 100,
                "saturateEnabled" : 0,
                "sepia" : 0,
                "sepiaEnabled" : 0,
                "top" : null,
                "visible" : true,
                "width" : 24,
                "widthType" : 0
              }
            ],
            "clip" : false,
            "codeOverrideEnabled" : false,
            "constraintsLocked" : false,
            "deviceType" : null,
            "exportOptions" : [

            ],
            "fillColor" : "rgba(255,255,255,1)",
            "fillEnabled" : false,
            "fillImage" : null,
            "fillImagePixelHeight" : null,
            "fillImagePixelWidth" : null,
            "fillImageResize" : "fill",
            "fillLinearGradient" : {
              "__class" : "LinearGradient",
              "alpha" : 1,
              "angle" : 180,
              "stops" : [
                {
                  "__class" : "GradientColorStop",
                  "position" : 0,
                  "value" : "rgba(0,0,0,0)"
                },
                {
                  "__class" : "GradientColorStop",
                  "position" : 1,
                  "value" : "black"
                }
              ]
            },
            "fillRadialGradient" : {
              "__class" : "RadialGradient",
              "alpha" : 1,
              "centerAnchorX" : 0.5,
              "centerAnchorY" : 0.5,
              "heightFactor" : 0.5,
              "stops" : [
                {
                  "__class" : "GradientColorStop",
                  "position" : 0,
                  "value" : "rgba(0,0,0,0)"
                },
                {
                  "__class" : "GradientColorStop",
                  "position" : 1,
                  "value" : "black"
                }
              ],
              "widthFactor" : 0.5
            },
            "fillType" : "color",
            "height" : 56,
            "heightType" : 0,
            "id" : "HSrCgvjbS",
            "intrinsicHeight" : null,
            "intrinsicWidth" : null,
            "isExternalMaster" : null,
            "isMaster" : false,
            "isTarget" : false,
            "left" : null,
            "locked" : false,
            "name" : null,
            "navigationTarget" : null,
            "navigationTransition" : "push",
            "navigationTransitionBackdropColor" : "rgba(4,4,15,.4)",
            "navigationTransitionDirection" : "left",
            "opacity" : 1,
            "originalid" : null,
            "parentid" : "rNqLB_W7W",
            "previewSettings" : null,
            "radius" : 0,
            "radiusBottomLeft" : 0,
            "radiusBottomRight" : 0,
            "radiusIsRelative" : false,
            "radiusPerCorner" : false,
            "radiusTopLeft" : 0,
            "radiusTopRight" : 0,
            "replicaInfo" : null,
            "right" : null,
            "rotation" : 0,
            "top" : 88,
            "visible" : true,
            "width" : 480,
            "widthType" : 0
          }
        ],
        "clip" : false,
        "codeOverrideEnabled" : false,
        "constraintsLocked" : false,
        "deviceType" : null,
        "exportOptions" : [
          {
            "__class" : "ExportOptions",
            "enabled" : true,
            "nameExtension" : "@2x",
            "nameExtensionMode" : "Suffix",
            "scale" : 2,
            "type" : "png"
          }
        ],
        "fillColor" : "rgba(102, 197, 255, 1.00)",
        "fillEnabled" : true,
        "fillImage" : null,
        "fillImagePixelHeight" : null,
        "fillImagePixelWidth" : null,
        "fillImageResize" : "fill",
        "fillLinearGradient" : {
          "__class" : "LinearGradient",
          "alpha" : 1,
          "angle" : 180,
          "stops" : [
            {
              "__class" : "GradientColorStop",
              "position" : 0,
              "value" : "rgba(0,0,0,0)"
            },
            {
              "__class" : "GradientColorStop",
              "position" : 1,
              "value" : "black"
            }
          ]
        },
        "fillRadialGradient" : {
          "__class" : "RadialGradient",
          "alpha" : 1,
          "centerAnchorX" : 0.5,
          "centerAnchorY" : 0.5,
          "heightFactor" : 0.5,
          "stops" : [
            {
              "__class" : "GradientColorStop",
              "position" : 0,
              "value" : "rgba(0,0,0,0)"
            },
            {
              "__class" : "GradientColorStop",
              "position" : 1,
              "value" : "black"
            }
          ],
          "widthFactor" : 0.5
        },
        "fillType" : "color",
        "height" : 600,
        "heightType" : 0,
        "id" : "rNqLB_W7W",
        "intrinsicHeight" : null,
        "intrinsicWidth" : null,
        "isExternalMaster" : null,
        "isMaster" : false,
        "isTarget" : false,
        "left" : 113,
        "locked" : false,
        "name" : "Screenshot",
        "navigationTarget" : null,
        "navigationTransition" : "push",
        "navigationTransitionBackdropColor" : "rgba(4,4,15,.4)",
        "navigationTransitionDirection" : "left",
        "opacity" : 1,
        "originalid" : null,
        "parentid" : "jT_RhS8r0",
        "previewSettings" : {
          "__class" : "PreviewSettings",
          "bezel" : false,
          "responsive" : false,
          "rotate" : false,
          "skin" : "",
          "touch" : true,
          "zoom" : -1
        },
        "radius" : 0,
        "radiusBottomLeft" : 0,
        "radiusBottomRight" : 0,
        "radiusIsRelative" : false,
        "radiusPerCorner" : false,
        "radiusTopLeft" : 0,
        "radiusTopRight" : 0,
        "replicaInfo" : null,
        "right" : null,
        "rotation" : 0,
        "top" : 181,
        "visible" : true,
        "width" : 800,
        "widthType" : 0
      },
      {
        "__class" : "FrameNode",
        "aspectRatio" : 1,
        "blendingEnabled" : 0,
        "blendingMode" : "normal",
        "blur" : 12,
        "blurEnabled" : 0,
        "blurType" : "layer",
        "borderBottom" : 1,
        "borderColor" : "#222",
        "borderEnabled" : 0,
        "borderLeft" : 1,
        "borderPerSide" : false,
        "borderRight" : 1,
        "borderStyle" : "solid",
        "borderTop" : 1,
        "borderWidth" : 1,
        "bottom" : null,
        "boxShadows" : [

        ],
        "brightness" : 100,
        "brightnessEnabled" : 0,
        "centerAnchorX" : 0,
        "centerAnchorY" : 0,
        "children" : [
          {
            "__class" : "SVGNode",
            "aspectRatio" : 1,
            "blendingEnabled" : 0,
            "blendingMode" : "normal",
            "blur" : 12,
            "blurEnabled" : 0,
            "blurType" : "layer",
            "bottom" : null,
            "brightness" : 100,
            "brightnessEnabled" : 0,
            "centerAnchorX" : 0.5,
            "centerAnchorY" : 0.5,
            "children" : [

            ],
            "colorable" : true,
            "constraintsLocked" : false,
            "contrast" : 100,
            "contrastEnabled" : 0,
            "exportOptions" : [
              {
                "__class" : "ExportOptions",
                "enabled" : true,
                "nameExtension" : "",
                "nameExtensionMode" : "Suffix",
                "scale" : 1,
                "type" : "png"
              }
            ],
            "fillColor" : "#555555",
            "fillImage" : null,
            "fillImagePixelHeight" : null,
            "fillImagePixelWidth" : null,
            "fillImageResize" : "fill",
            "fillLinearGradient" : {
              "__class" : "LinearGradient",
              "alpha" : 1,
              "angle" : 180,
              "stops" : [
                {
                  "__class" : "GradientColorStop",
                  "position" : 0,
                  "value" : "rgba(0,0,0,0)"
                },
                {
                  "__class" : "GradientColorStop",
                  "position" : 1,
                  "value" : "black"
                }
              ]
            },
            "fillRadialGradient" : {
              "__class" : "RadialGradient",
              "alpha" : 1,
              "centerAnchorX" : 0.5,
              "centerAnchorY" : 0.5,
              "heightFactor" : 0.5,
              "stops" : [
                {
                  "__class" : "GradientColorStop",
                  "position" : 0,
                  "value" : "rgba(0,0,0,0)"
                },
                {
                  "__class" : "GradientColorStop",
                  "position" : 1,
                  "value" : "black"
                }
              ],
              "widthFactor" : 0.5
            },
            "fillType" : "color",
            "grayscale" : 0,
            "grayScaleEnabled" : 0,
            "height" : 24,
            "heightType" : 0,
            "hueRotate" : 0,
            "hueRotateEnabled" : 0,
            "id" : "@framer\/colebemis.feather-icons-kJVk7KBWG-uDQ947E3A",
            "intrinsicHeight" : 24,
            "intrinsicWidth" : 24,
            "invert" : 0,
            "invertEnabled" : 0,
            "left" : 0,
            "locked" : false,
            "name" : null,
            "opacity" : 1,
            "originalFilename" : "search.svg",
            "originalid" : null,
            "parentid" : "@framer\/colebemis.feather-icons-kJVk7KBWG",
            "right" : 0,
            "rotation" : 0,
            "saturate" : 100,
            "saturateEnabled" : 0,
            "sepia" : 0,
            "sepiaEnabled" : 0,
            "shadows" : [

            ],
            "svg" : "<?xml version=\"1.0\"?><svg xmlns=\"http:\/\/www.w3.org\/2000\/svg\" width=\"24\" height=\"24\" fill=\"none\" stroke=\"currentColor\" stroke-width=\"2\" stroke-linecap=\"round\" stroke-linejoin=\"round\" class=\"feather feather-search\"><circle cx=\"11\" cy=\"11\" r=\"8\"><\/circle><path d=\"M21 21l-4.35-4.35\"><\/path><\/svg>",
            "top" : 0,
            "visible" : true,
            "width" : 24,
            "widthType" : 0
          }
        ],
        "clip" : true,
        "codeOverrideEnabled" : false,
        "constraintsLocked" : false,
        "contrast" : 100,
        "contrastEnabled" : 0,
        "deviceType" : null,
        "exportOptions" : [
          {
            "__class" : "ExportOptions",
            "enabled" : true,
            "nameExtension" : "",
            "nameExtensionMode" : "Suffix",
            "scale" : 1,
            "type" : "png"
          }
        ],
        "fillColor" : "rgba(255,255,255,1)",
        "fillEnabled" : false,
        "fillImage" : null,
        "fillImagePixelHeight" : null,
        "fillImagePixelWidth" : null,
        "fillImageResize" : "fill",
        "fillLinearGradient" : {
          "__class" : "LinearGradient",
          "alpha" : 1,
          "angle" : 180,
          "stops" : [
            {
              "__class" : "GradientColorStop",
              "position" : 0,
              "value" : "rgba(0,0,0,0)"
            },
            {
              "__class" : "GradientColorStop",
              "position" : 1,
              "value" : "black"
            }
          ]
        },
        "fillRadialGradient" : {
          "__class" : "RadialGradient",
          "alpha" : 1,
          "centerAnchorX" : 0.5,
          "centerAnchorY" : 0.5,
          "heightFactor" : 0.5,
          "stops" : [
            {
              "__class" : "GradientColorStop",
              "position" : 0,
              "value" : "rgba(0,0,0,0)"
            },
            {
              "__class" : "GradientColorStop",
              "position" : 1,
              "value" : "black"
            }
          ],
          "widthFactor" : 0.5
        },
        "fillType" : "color",
        "grayscale" : 0,
        "grayScaleEnabled" : 0,
        "height" : 24,
        "heightType" : 0,
        "hueRotate" : 0,
        "hueRotateEnabled" : 0,
        "id" : "@framer\/colebemis.feather-icons-kJVk7KBWG",
        "intrinsicHeight" : null,
        "intrinsicWidth" : null,
        "invert" : 0,
        "invertEnabled" : 0,
        "isExternalMaster" : "@framer\/colebemis.feather-icons",
        "isMaster" : true,
        "isTarget" : false,
        "left" : 0,
        "locked" : false,
        "name" : "search",
        "navigationTarget" : null,
        "navigationTransition" : "push",
        "navigationTransitionBackdropColor" : "rgba(4,4,15,.4)",
        "navigationTransitionDirection" : "left",
        "opacity" : 1,
        "originalid" : null,
        "parentid" : "jT_RhS8r0",
        "previewSettings" : null,
        "radius" : 0,
        "radiusBottomLeft" : 0,
        "radiusBottomRight" : 0,
        "radiusIsRelative" : false,
        "radiusPerCorner" : false,
        "radiusTopLeft" : 0,
        "radiusTopRight" : 0,
        "replicaInfo" : null,
        "right" : null,
        "rotation" : 0,
        "saturate" : 100,
        "saturateEnabled" : 0,
        "sepia" : 0,
        "sepiaEnabled" : 0,
        "top" : 0,
        "visible" : true,
        "width" : 24,
        "widthType" : 0
      },
      {
        "__class" : "FrameNode",
        "aspectRatio" : null,
        "blendingEnabled" : 0,
        "blendingMode" : "normal",
        "bottom" : null,
        "centerAnchorX" : 0,
        "centerAnchorY" : 0,
        "children" : [
          {
            "__class" : "FrameNode",
            "aspectRatio" : null,
            "blendingEnabled" : 0,
            "blendingMode" : "normal",
            "bottom" : null,
            "centerAnchorX" : 0.5,
            "centerAnchorY" : 0.48999999999999999,
            "children" : [
              {
                "__class" : "FrameNode",
                "aspectRatio" : null,
                "blendingEnabled" : 0,
                "blendingMode" : "normal",
                "bottom" : null,
                "centerAnchorX" : 0.5,
                "centerAnchorY" : 0.22222222222222221,
                "children" : [
                  {
                    "__class" : "FrameNode",
                    "aspectRatio" : 1,
                    "blendingEnabled" : 0,
                    "blendingMode" : "normal",
                    "blur" : 12,
                    "blurEnabled" : 0,
                    "blurType" : "layer",
                    "borderBottom" : 1,
                    "borderColor" : "#222",
                    "borderEnabled" : 0,
                    "borderLeft" : 1,
                    "borderPerSide" : false,
                    "borderRight" : 1,
                    "borderStyle" : "solid",
                    "borderTop" : 1,
                    "borderWidth" : 1,
                    "bottom" : null,
                    "boxShadows" : [

                    ],
                    "brightness" : 100,
                    "brightnessEnabled" : 0,
                    "centerAnchorX" : 0.5,
                    "centerAnchorY" : 0.5,
                    "children" : [

                    ],
                    "clip" : true,
                    "codeOverrideEnabled" : false,
                    "constraintsLocked" : false,
                    "contrast" : 100,
                    "contrastEnabled" : 0,
                    "deviceType" : null,
                    "exportOptions" : [
                      {
                        "__class" : "ExportOptions",
                        "enabled" : true,
                        "nameExtension" : "",
                        "nameExtensionMode" : "Suffix",
                        "scale" : 1,
                        "type" : "png"
                      }
                    ],
                    "fillColor" : "rgba(255,255,255,1)",
                    "fillEnabled" : false,
                    "fillImage" : null,
                    "fillImagePixelHeight" : null,
                    "fillImagePixelWidth" : null,
                    "fillImageResize" : "fill",
                    "fillLinearGradient" : {
                      "__class" : "LinearGradient",
                      "alpha" : 1,
                      "angle" : 180,
                      "stops" : [
                        {
                          "__class" : "GradientColorStop",
                          "position" : 0,
                          "value" : "rgba(0,0,0,0)"
                        },
                        {
                          "__class" : "GradientColorStop",
                          "position" : 1,
                          "value" : "black"
                        }
                      ]
                    },
                    "fillRadialGradient" : {
                      "__class" : "RadialGradient",
                      "alpha" : 1,
                      "centerAnchorX" : 0.5,
                      "centerAnchorY" : 0.5,
                      "heightFactor" : 0.5,
                      "stops" : [
                        {
                          "__class" : "GradientColorStop",
                          "position" : 0,
                          "value" : "rgba(0,0,0,0)"
                        },
                        {
                          "__class" : "GradientColorStop",
                          "position" : 1,
                          "value" : "black"
                        }
                      ],
                      "widthFactor" : 0.5
                    },
                    "fillType" : "color",
                    "grayscale" : 0,
                    "grayScaleEnabled" : 0,
                    "height" : 6,
                    "heightType" : 0,
                    "hueRotate" : 0,
                    "hueRotateEnabled" : 0,
                    "id" : "eWlRolyUo",
                    "intrinsicHeight" : null,
                    "intrinsicWidth" : null,
                    "invert" : 0,
                    "invertEnabled" : 0,
                    "isExternalMaster" : null,
                    "isMaster" : false,
                    "isTarget" : false,
                    "left" : null,
                    "locked" : false,
                    "name" : "search",
                    "navigationTarget" : null,
                    "navigationTransition" : "push",
                    "navigationTransitionBackdropColor" : "rgba(4,4,15,.4)",
                    "navigationTransitionDirection" : "left",
                    "opacity" : 1,
                    "originalid" : "@framer\/colebemis.feather-icons-kJVk7KBWG",
                    "parentid" : "Zm3hpkJLU",
                    "previewSettings" : null,
                    "radius" : 0,
                    "radiusBottomLeft" : 0,
                    "radiusBottomRight" : 0,
                    "radiusIsRelative" : false,
                    "radiusPerCorner" : false,
                    "radiusTopLeft" : 0,
                    "radiusTopRight" : 0,
                    "replicaInfo" : {
                      "master" : "@framer\/colebemis.feather-icons-kJVk7KBWG",
                      "overrides" : {
                        "@framer\/colebemis.feather-icons-kJVk7KBWG" : {
                          "bottom" : null,
                          "centerAnchorX" : 0.5,
                          "centerAnchorY" : 0.5,
                          "height" : 6,
                          "left" : null,
                          "right" : null,
                          "top" : null,
                          "width" : 6
                        },
                        "@framer\/colebemis.feather-icons-kJVk7KBWG-uDQ947E3A" : {

                        }
                      }
                    },
                    "right" : null,
                    "rotation" : 0,
                    "saturate" : 100,
                    "saturateEnabled" : 0,
                    "sepia" : 0,
                    "sepiaEnabled" : 0,
                    "top" : null,
                    "visible" : true,
                    "width" : 6,
                    "widthType" : 0
                  }
                ],
                "clip" : false,
                "codeOverrideEnabled" : false,
                "constraintsLocked" : false,
                "deviceType" : null,
                "exportOptions" : [

                ],
                "fillColor" : "rgb(255, 255, 255)",
                "fillEnabled" : true,
                "fillImage" : null,
                "fillImagePixelHeight" : null,
                "fillImagePixelWidth" : null,
                "fillImageResize" : "fill",
                "fillLinearGradient" : {
                  "__class" : "LinearGradient",
                  "alpha" : 1,
                  "angle" : 180,
                  "stops" : [
                    {
                      "__class" : "GradientColorStop",
                      "position" : 0,
                      "value" : "rgba(0,0,0,0)"
                    },
                    {
                      "__class" : "GradientColorStop",
                      "position" : 1,
                      "value" : "black"
                    }
                  ]
                },
                "fillRadialGradient" : {
                  "__class" : "RadialGradient",
                  "alpha" : 1,
                  "centerAnchorX" : 0.5,
                  "centerAnchorY" : 0.5,
                  "heightFactor" : 0.5,
                  "stops" : [
                    {
                      "__class" : "GradientColorStop",
                      "position" : 0,
                      "value" : "rgba(0,0,0,0)"
                    },
                    {
                      "__class" : "GradientColorStop",
                      "position" : 1,
                      "value" : "black"
                    }
                  ],
                  "widthFactor" : 0.5
                },
                "fillType" : "color",
                "height" : 12,
                "heightType" : 0,
                "id" : "Zm3hpkJLU",
                "intrinsicHeight" : null,
                "intrinsicWidth" : null,
                "isExternalMaster" : null,
                "isMaster" : false,
                "isTarget" : false,
                "left" : 0,
                "locked" : false,
                "name" : null,
                "navigationTarget" : null,
                "navigationTransition" : "push",
                "navigationTransitionBackdropColor" : "rgba(4,4,15,.4)",
                "navigationTransitionDirection" : "left",
                "opacity" : 1,
                "originalid" : null,
                "parentid" : "UsbcuVyGk",
                "previewSettings" : null,
                "radius" : 2,
                "radiusBottomLeft" : 2,
                "radiusBottomRight" : 2,
                "radiusIsRelative" : false,
                "radiusPerCorner" : false,
                "radiusTopLeft" : 2,
                "radiusTopRight" : 2,
                "replicaInfo" : null,
                "right" : 0,
                "rotation" : 0,
                "top" : 0,
                "visible" : true,
                "width" : 24,
                "widthType" : 0
              },
              {
                "__class" : "FrameNode",
                "aspectRatio" : null,
                "blendingEnabled" : 0,
                "blendingMode" : "normal",
                "bottom" : 7,
                "centerAnchorX" : 0.5,
                "centerAnchorY" : 0.61111111111111116,
                "children" : [

                ],
                "clip" : false,
                "codeOverrideEnabled" : false,
                "constraintsLocked" : false,
                "deviceType" : null,
                "exportOptions" : [

                ],
                "fillColor" : "rgba(255, 255, 255, 0.8)",
                "fillEnabled" : true,
                "fillImage" : null,
                "fillImagePixelHeight" : null,
                "fillImagePixelWidth" : null,
                "fillImageResize" : "fill",
                "fillLinearGradient" : {
                  "__class" : "LinearGradient",
                  "alpha" : 1,
                  "angle" : 180,
                  "stops" : [
                    {
                      "__class" : "GradientColorStop",
                      "position" : 0,
                      "value" : "rgba(0,0,0,0)"
                    },
                    {
                      "__class" : "GradientColorStop",
                      "position" : 1,
                      "value" : "black"
                    }
                  ]
                },
                "fillRadialGradient" : {
                  "__class" : "RadialGradient",
                  "alpha" : 1,
                  "centerAnchorX" : 0.5,
                  "centerAnchorY" : 0.5,
                  "heightFactor" : 0.5,
                  "stops" : [
                    {
                      "__class" : "GradientColorStop",
                      "position" : 0,
                      "value" : "rgba(0,0,0,0)"
                    },
                    {
                      "__class" : "GradientColorStop",
                      "position" : 1,
                      "value" : "black"
                    }
                  ],
                  "widthFactor" : 0.5
                },
                "fillType" : "color",
                "height" : 7,
                "heightType" : 0,
                "id" : "FCjtoVtKl",
                "intrinsicHeight" : null,
                "intrinsicWidth" : null,
                "isExternalMaster" : null,
                "isMaster" : false,
                "isTarget" : false,
                "left" : 0,
                "locked" : false,
                "name" : null,
                "navigationTarget" : null,
                "navigationTransition" : "push",
                "navigationTransitionBackdropColor" : "rgba(4,4,15,.4)",
                "navigationTransitionDirection" : "left",
                "opacity" : 1,
                "originalid" : null,
                "parentid" : "UsbcuVyGk",
                "previewSettings" : null,
                "radius" : 2,
                "radiusBottomLeft" : 0,
                "radiusBottomRight" : 0,
                "radiusIsRelative" : false,
                "radiusPerCorner" : true,
                "radiusTopLeft" : 2,
                "radiusTopRight" : 2,
                "replicaInfo" : null,
                "right" : 0,
                "rotation" : 0,
                "top" : null,
                "visible" : true,
                "width" : 24,
                "widthType" : 0
              },
              {
                "__class" : "FrameNode",
                "aspectRatio" : null,
                "blendingEnabled" : 0,
                "blendingMode" : "normal",
                "bottom" : 0,
                "centerAnchorX" : 0.5,
                "centerAnchorY" : 0.87037037037037035,
                "children" : [

                ],
                "clip" : false,
                "codeOverrideEnabled" : false,
                "constraintsLocked" : false,
                "deviceType" : null,
                "exportOptions" : [

                ],
                "fillColor" : "rgba(255, 255, 255, 0.4)",
                "fillEnabled" : true,
                "fillImage" : null,
                "fillImagePixelHeight" : null,
                "fillImagePixelWidth" : null,
                "fillImageResize" : "fill",
                "fillLinearGradient" : {
                  "__class" : "LinearGradient",
                  "alpha" : 1,
                  "angle" : 180,
                  "stops" : [
                    {
                      "__class" : "GradientColorStop",
                      "position" : 0,
                      "value" : "rgba(0,0,0,0)"
                    },
                    {
                      "__class" : "GradientColorStop",
                      "position" : 1,
                      "value" : "black"
                    }
                  ]
                },
                "fillRadialGradient" : {
                  "__class" : "RadialGradient",
                  "alpha" : 1,
                  "centerAnchorX" : 0.5,
                  "centerAnchorY" : 0.5,
                  "heightFactor" : 0.5,
                  "stops" : [
                    {
                      "__class" : "GradientColorStop",
                      "position" : 0,
                      "value" : "rgba(0,0,0,0)"
                    },
                    {
                      "__class" : "GradientColorStop",
                      "position" : 1,
                      "value" : "black"
                    }
                  ],
                  "widthFactor" : 0.5
                },
                "fillType" : "color",
                "height" : 7,
                "heightType" : 0,
                "id" : "qk1NGIv2P",
                "intrinsicHeight" : null,
                "intrinsicWidth" : null,
                "isExternalMaster" : null,
                "isMaster" : false,
                "isTarget" : false,
                "left" : 0,
                "locked" : false,
                "name" : null,
                "navigationTarget" : null,
                "navigationTransition" : "push",
                "navigationTransitionBackdropColor" : "rgba(4,4,15,.4)",
                "navigationTransitionDirection" : "left",
                "opacity" : 1,
                "originalid" : null,
                "parentid" : "UsbcuVyGk",
                "previewSettings" : null,
                "radius" : 2,
                "radiusBottomLeft" : 2,
                "radiusBottomRight" : 2,
                "radiusIsRelative" : false,
                "radiusPerCorner" : true,
                "radiusTopLeft" : 0,
                "radiusTopRight" : 0,
                "replicaInfo" : null,
                "right" : 0,
                "rotation" : 0,
                "top" : null,
                "visible" : true,
                "width" : 24,
                "widthType" : 0
              }
            ],
            "clip" : false,
            "codeOverrideEnabled" : false,
            "constraintsLocked" : false,
            "deviceType" : null,
            "exportOptions" : [

            ],
            "fillColor" : "rgba(255,255,255,1)",
            "fillEnabled" : false,
            "fillImage" : null,
            "fillImagePixelHeight" : null,
            "fillImagePixelWidth" : null,
            "fillImageResize" : "fill",
            "fillLinearGradient" : {
              "__class" : "LinearGradient",
              "alpha" : 1,
              "angle" : 180,
              "stops" : [
                {
                  "__class" : "GradientColorStop",
                  "position" : 0,
                  "value" : "rgba(0,0,0,0)"
                },
                {
                  "__class" : "GradientColorStop",
                  "position" : 1,
                  "value" : "black"
                }
              ]
            },
            "fillRadialGradient" : {
              "__class" : "RadialGradient",
              "alpha" : 1,
              "centerAnchorX" : 0.5,
              "centerAnchorY" : 0.5,
              "heightFactor" : 0.5,
              "stops" : [
                {
                  "__class" : "GradientColorStop",
                  "position" : 0,
                  "value" : "rgba(0,0,0,0)"
                },
                {
                  "__class" : "GradientColorStop",
                  "position" : 1,
                  "value" : "black"
                }
              ],
              "widthFactor" : 0.5
            },
            "fillType" : "color",
            "height" : 27,
            "heightType" : 0,
            "id" : "UsbcuVyGk",
            "intrinsicHeight" : null,
            "intrinsicWidth" : null,
            "isExternalMaster" : null,
            "isMaster" : false,
            "isTarget" : false,
            "left" : null,
            "locked" : false,
            "name" : null,
            "navigationTarget" : null,
            "navigationTransition" : "push",
            "navigationTransitionBackdropColor" : "rgba(4,4,15,.4)",
            "navigationTransitionDirection" : "left",
            "opacity" : 1,
            "originalid" : null,
            "parentid" : "pFpBvyOcQ",
            "previewSettings" : null,
            "radius" : 0,
            "radiusBottomLeft" : 0,
            "radiusBottomRight" : 0,
            "radiusIsRelative" : false,
            "radiusPerCorner" : false,
            "radiusTopLeft" : 0,
            "radiusTopRight" : 0,
            "replicaInfo" : null,
            "right" : null,
            "rotation" : 0,
            "top" : null,
            "visible" : true,
            "width" : 24,
            "widthType" : 0
          }
        ],
        "clip" : true,
        "codeOverrideEnabled" : false,
        "constraintsLocked" : false,
        "deviceType" : "framer\/FramerStoreIcon",
        "exportOptions" : [
          {
            "__class" : "ExportOptions",
            "enabled" : true,
            "nameExtension" : "@2x",
            "nameExtensionMode" : "Suffix",
            "scale" : 2,
            "type" : "png"
          }
        ],
        "fillColor" : "#1199EE",
        "fillEnabled" : true,
        "fillImage" : null,
        "fillImagePixelHeight" : null,
        "fillImagePixelWidth" : null,
        "fillImageResize" : "fill",
        "fillLinearGradient" : {
          "__class" : "LinearGradient",
          "alpha" : 1,
          "angle" : 180,
          "stops" : [
            {
              "__class" : "GradientColorStop",
              "position" : 0,
              "value" : "rgba(0,0,0,0)"
            },
            {
              "__class" : "GradientColorStop",
              "position" : 1,
              "value" : "black"
            }
          ]
        },
        "fillRadialGradient" : {
          "__class" : "RadialGradient",
          "alpha" : 1,
          "centerAnchorX" : 0.5,
          "centerAnchorY" : 0.5,
          "heightFactor" : 0.5,
          "stops" : [
            {
              "__class" : "GradientColorStop",
              "position" : 0,
              "value" : "rgba(0,0,0,0)"
            },
            {
              "__class" : "GradientColorStop",
              "position" : 1,
              "value" : "black"
            }
          ],
          "widthFactor" : 0.5
        },
        "fillType" : "color",
        "height" : 50,
        "heightType" : 0,
        "id" : "pFpBvyOcQ",
        "intrinsicHeight" : null,
        "intrinsicWidth" : null,
        "isExternalMaster" : null,
        "isMaster" : false,
        "isTarget" : false,
        "left" : 1013,
        "locked" : false,
        "name" : null,
        "navigationTarget" : null,
        "navigationTransition" : "push",
        "navigationTransitionBackdropColor" : "rgba(4,4,15,.4)",
        "navigationTransitionDirection" : "left",
        "opacity" : 1,
        "originalid" : null,
        "parentid" : "jT_RhS8r0",
        "previewSettings" : {
          "__class" : "PreviewSettings",
          "bezel" : false,
          "deviceType" : "framer\/FramerStoreIcon",
          "responsive" : true,
          "rotate" : false,
          "touch" : true,
          "zoom" : -1
        },
        "radius" : 0,
        "radiusBottomLeft" : 0,
        "radiusBottomRight" : 0,
        "radiusIsRelative" : false,
        "radiusPerCorner" : false,
        "radiusTopLeft" : 0,
        "radiusTopRight" : 0,
        "replicaInfo" : null,
        "right" : null,
        "rotation" : 0,
        "top" : 181,
        "visible" : true,
        "width" : 50,
        "widthType" : 0
      },
      {
        "__class" : "FrameNode",
        "aspectRatio" : null,
        "blendingEnabled" : 0,
        "blendingMode" : "normal",
        "bottom" : null,
        "centerAnchorX" : 0,
        "centerAnchorY" : 0,
        "children" : [
          {
            "__class" : "CodeComponentNode",
            "aspectRatio" : null,
            "bottom" : null,
            "centerAnchorX" : 0.5,
            "centerAnchorY" : 0.30714285714285716,
            "children" : [

            ],
            "clip" : true,
            "codeComponentIdentifier" : ".\/Input.tsx_Input",
            "codeComponentProps" : {
              "placeholder" : "0",
              "type" : "text"
            },
            "codeOverrideEnabled" : true,
            "codeOverrideFile" : ".\/InputOverrides.tsx",
            "codeOverrideIdentifier" : ".\/InputOverrides.tsx_InputEvents",
            "codeOverrideName" : "InputEvents",
            "constraintsLocked" : false,
            "deviceType" : null,
            "exportOptions" : [

            ],
            "fillColor" : "rgba(255,255,255,1)",
            "fillEnabled" : false,
            "fillImage" : null,
            "fillImagePixelHeight" : null,
            "fillImagePixelWidth" : null,
            "fillImageResize" : "fill",
            "fillLinearGradient" : {
              "__class" : "LinearGradient",
              "alpha" : 1,
              "angle" : 180,
              "stops" : [
                {
                  "__class" : "GradientColorStop",
                  "position" : 0,
                  "value" : "rgba(0,0,0,0)"
                },
                {
                  "__class" : "GradientColorStop",
                  "position" : 1,
                  "value" : "black"
                }
              ]
            },
            "fillRadialGradient" : {
              "__class" : "RadialGradient",
              "alpha" : 1,
              "centerAnchorX" : 0.5,
              "centerAnchorY" : 0.5,
              "heightFactor" : 0.5,
              "stops" : [
                {
                  "__class" : "GradientColorStop",
                  "position" : 0,
                  "value" : "rgba(0,0,0,0)"
                },
                {
                  "__class" : "GradientColorStop",
                  "position" : 1,
                  "value" : "black"
                }
              ],
              "widthFactor" : 0.5
            },
            "fillType" : "color",
            "height" : 48,
            "heightType" : 0,
            "id" : "qeOlFjWmG",
            "intrinsicHeight" : 48,
            "intrinsicWidth" : 200,
            "left" : 84,
            "locked" : false,
            "name" : null,
            "opacity" : 1,
            "originalid" : null,
            "parentid" : "SaNhzNzXF",
            "previewSettings" : null,
            "radius" : 0,
            "radiusBottomLeft" : 0,
            "radiusBottomRight" : 0,
            "radiusIsRelative" : false,
            "radiusPerCorner" : false,
            "radiusTopLeft" : 0,
            "radiusTopRight" : 0,
            "right" : 84,
            "rotation" : 0,
            "top" : 62,
            "visible" : true,
            "width" : 429,
            "widthType" : 0
          },
          {
            "__class" : "TextNode",
            "autoSize" : true,
            "bottom" : 100,
            "centerAnchorX" : 0.19932998324958123,
            "centerAnchorY" : 0.60892857142857137,
            "codeOverrideEnabled" : true,
            "codeOverrideFile" : ".\/InputOverrides.tsx",
            "codeOverrideIdentifier" : ".\/InputOverrides.tsx_Output",
            "codeOverrideName" : "Output",
            "constraintsLocked" : false,
            "exportOptions" : [

            ],
            "height" : 19,
            "heightType" : 0,
            "id" : "ioGvRqkbB",
            "isTarget" : false,
            "left" : 119,
            "locked" : false,
            "name" : null,
            "opacity" : 1,
            "originalid" : null,
            "parentid" : "SaNhzNzXF",
            "right" : null,
            "rotation" : 0,
            "styledText" : {
              "__class" : "StyledTextDraft",
              "blocks" : [
                {
                  "data" : {
                    "emptyStyle" : [
                      "FONT:__SF-UI-Text-Regular__",
                      "COLOR:rgb(0, 0, 0)",
                      "SIZE:16",
                      "LETTERSPACING:0",
                      "LINEHEIGHT:1.2"
                    ]
                  },
                  "depth" : 0,
                  "entityRanges" : [

                  ],
                  "inlineStyleRanges" : [
                    {
                      "length" : 6,
                      "offset" : 0,
                      "style" : "FONT:__SF-UI-Text-Regular__"
                    },
                    {
                      "length" : 6,
                      "offset" : 0,
                      "style" : "COLOR:rgb(0, 0, 0)"
                    },
                    {
                      "length" : 6,
                      "offset" : 0,
                      "style" : "SIZE:16"
                    },
                    {
                      "length" : 6,
                      "offset" : 0,
                      "style" : "LETTERSPACING:0"
                    },
                    {
                      "length" : 6,
                      "offset" : 0,
                      "style" : "LINEHEIGHT:1.2"
                    }
                  ],
                  "key" : "2088r",
                  "text" : "Output",
                  "type" : "unstyled"
                }
              ],
              "cached" : {
                "html" : "<div data-offset-key=\"2088r-0-0\" class=\"public-DraftStyleDefault-block public-DraftStyleDefault-ltr\"><span data-offset-key=\"2088r-0-0\" style=\"tab-size:4;font-family:&quot;.SFNSText&quot;, &quot;SFProText-Regular&quot;, &quot;SFUIText-Regular&quot;, &quot;.SFUIText&quot;, sans-serif;-webkit-text-fill-color:rgb(0, 0, 0);font-size:16px;letter-spacing:0px;line-height:1.2\"><span data-text=\"true\">Output<\/span><\/span><\/div>",
                "os" : "10_14",
                "size" : {
                  "height" : 19,
                  "width" : 54
                },
                "width" : 0
              },
              "entityMap" : {

              }
            },
            "top" : null,
            "visible" : true,
            "width" : 54,
            "widthType" : 0,
            "x" : 119,
            "y" : 180
          }
        ],
        "clip" : true,
        "codeOverrideEnabled" : false,
        "constraintsLocked" : false,
        "deviceType" : null,
        "exportOptions" : [

        ],
        "fillColor" : "white",
        "fillEnabled" : true,
        "fillImage" : null,
        "fillImagePixelHeight" : null,
        "fillImagePixelWidth" : null,
        "fillImageResize" : "fill",
        "fillLinearGradient" : {
          "__class" : "LinearGradient",
          "alpha" : 1,
          "angle" : 180,
          "stops" : [
            {
              "__class" : "GradientColorStop",
              "position" : 0,
              "value" : "rgba(0,0,0,0)"
            },
            {
              "__class" : "GradientColorStop",
              "position" : 1,
              "value" : "black"
            }
          ]
        },
        "fillRadialGradient" : {
          "__class" : "RadialGradient",
          "alpha" : 1,
          "centerAnchorX" : 0.5,
          "centerAnchorY" : 0.5,
          "heightFactor" : 0.5,
          "stops" : [
            {
              "__class" : "GradientColorStop",
              "position" : 0,
              "value" : "rgba(0,0,0,0)"
            },
            {
              "__class" : "GradientColorStop",
              "position" : 1,
              "value" : "black"
            }
          ],
          "widthFactor" : 0.5
        },
        "fillType" : "color",
        "height" : 280,
        "heightType" : 0,
        "id" : "SaNhzNzXF",
        "intrinsicHeight" : null,
        "intrinsicWidth" : null,
        "isExternalMaster" : null,
        "isMaster" : false,
        "isTarget" : false,
        "left" : 137,
        "locked" : false,
        "name" : null,
        "navigationTarget" : null,
        "navigationTransition" : "push",
        "navigationTransitionBackdropColor" : "rgba(4,4,15,.4)",
        "navigationTransitionDirection" : "left",
        "opacity" : 1,
        "originalid" : null,
        "parentid" : "jT_RhS8r0",
        "previewSettings" : null,
        "radius" : 0,
        "radiusBottomLeft" : 0,
        "radiusBottomRight" : 0,
        "radiusIsRelative" : false,
        "radiusPerCorner" : false,
        "radiusTopLeft" : 0,
        "radiusTopRight" : 0,
        "replicaInfo" : null,
        "right" : null,
        "rotation" : 0,
        "top" : 911,
        "visible" : true,
        "width" : 597,
        "widthType" : 0
      }
    ],
    "id" : "jT_RhS8r0",
    "name" : null,
    "originalid" : null,
    "parentid" : null,
    "tokens" : {

    },
    "tokensIndex" : [

    ],
    "visible" : false
  },
  "version" : 52
}